[
  {"name": "Pure White",                    "rgb": [255, 255, 255]},
  {"name": "Soft White/Cream",              "rgb": [245, 240, 225]},
  {"name": "Aran/Bone",                     "rgb": [235, 225, 205]},
  {"name": "Oatmeal/Heather",               "rgb": [220, 210, 195]},
  {"name": "Buff/Beige",                    "rgb": [230, 205, 175]},
  {"name": "Warm Tan",                      "rgb": [210, 180, 140]},
  {"name": "Cafe Latte",                    "rgb": [185, 150, 120]},
  {"name": "Milk Chocolate",                "rgb": [135, 90, 60]},
  {"name": "Dark Coffee",                   "rgb": [80, 50, 40]},

  {"name": "Silver/Light Grey",             "rgb": [208, 208, 192]},
  {"name": "Heather Grey",                  "rgb": [170, 170, 175]},
  {"name": "Dusty Grey",                    "rgb": [160, 160, 165]},
  {"name": "Charcoal",                      "rgb": [75, 75, 80]},
  {"name": "Soft Black",                    "rgb": [30, 30, 30]},
  {"name": "Pitch Black",                   "rgb": [10, 10, 10]},

  {"name": "Pale Yellow",                   "rgb": [255, 255, 150]},
  {"name": "Lemon",                         "rgb": [255, 245, 100]},
  {"name": "Sunflower/Bright Yellow",       "rgb": [255, 215, 0]},
  {"name": "Mustard/Gold",                  "rgb": [215, 165, 30]},

  {"name": "Peach",                         "rgb": [255, 218, 185]},
  {"name": "Coral",                         "rgb": [245, 150, 130]},
  {"name": "Pumpkin/Orange",                "rgb": [235, 115, 30]},
  {"name": "Burnt Orange/Rust",             "rgb": [180, 70, 20]},

  {"name": "Baby Pink",                     "rgb": [255, 192, 203]},
  {"name": "Petal Pink",                    "rgb": [255, 190, 200]},
  {"name": "Bubblegum Pink",                "rgb": [255, 105, 180]},
  {"name": "Magenta/Fuchsia",               "rgb": [225, 50, 130]},
  {"name": "Cherry Red",                    "rgb": [200, 25, 35]},
  {"name": "Crimson",                       "rgb": [180, 10, 20]},
  {"name": "Burgundy/Wine",                 "rgb": [115, 25, 40]},

  {"name": "Lilac/Pale Purple",             "rgb": [216, 191, 216]},
  {"name": "Lavender",                      "rgb": [200, 170, 220]},
  {"name": "Amethyst",                      "rgb": [135, 70, 160]},
  {"name": "Deep Plum",                     "rgb": [85, 40, 95]},
  {"name": "Eggplant",                      "rgb": [60, 20, 60]},

  {"name": "Baby Blue",                     "rgb": [173, 216, 230]},
  {"name": "Sky Blue",                      "rgb": [135, 206, 235]},
  {"name": "Cornflower Blue",               "rgb": [100, 149, 237]},
  {"name": "Country Blue",                  "rgb": [100, 130, 170]},
  {"name": "Royal Blue",                    "rgb": [30, 80, 180]},
  {"name": "Navy Blue",                     "rgb": [25, 40, 85]},
  {"name": "Midnight Blue",                 "rgb": [15, 20, 50]},

  {"name": "Mint Green",                    "rgb": [170, 230, 200]},
  {"name": "Seafoam",                       "rgb": [143, 188, 143]},
  {"name": "Spring Green",                  "rgb": [140, 200, 115]},
  {"name": "Kelly Green",                   "rgb": [40, 145, 60]},
  {"name": "Hunter Green",                  "rgb": [30, 85, 50]},
  {"name": "Sage Green",                    "rgb": [130, 150, 120]},
  {"name": "Olive Green",                   "rgb": [85, 107, 47]},

  {"name": "Aqua",                          "rgb": [0, 255, 255]},
  {"name": "Turquoise",                     "rgb": [45, 180, 190]},
  {"name": "Teal",                          "rgb": [20, 110, 120]},
  {"name": "Peacock",                       "rgb": [10, 80, 100]},

  {"name": "Terracotta",                    "rgb": [204, 78, 44]},
  {"name": "Mustard Yellow",                "rgb": [224, 171, 38]},
  {"name": "Olive Green",                   "rgb": [128, 128, 0]},
  {"name": "Forest Green",                  "rgb": [34, 139, 34]},
  {"name": "Dusty Rose",                    "rgb": [202, 139, 147]},
  {"name": "Mushroom/Taupe",                "rgb": [175, 164, 148]},
  {"name": "Rust",                          "rgb": [183, 65, 14]},

  {"name": "Emerald",                       "rgb": [8, 143, 60]},
  {"name": "Sapphire Blue",                 "rgb": [15, 82, 186]},
  {"name": "Ruby Red",                      "rgb": [224, 17, 95]},
  {"name": "Deep Magenta",                  "rgb": [180, 24, 114]},
  {"name": "Peacock Blue",                  "rgb": [51, 161, 201]},
  {"name": "Eggplant",                      "rgb": [97, 64, 81]},

  {"name": "Baby Pink",                     "rgb": [255, 182, 193]},
  {"name": "Powder Blue",                   "rgb": [176, 224, 230]},
  {"name": "Pale Lemon",                    "rgb": [255, 250, 205]},
  {"name": "Mint Ice",                      "rgb": [189, 252, 201]},
  {"name": "Soft Lilac",                    "rgb": [216, 191, 216]},
  {"name": "Peach Whip",                    "rgb": [255, 218, 185]},

  {"name": "Neon Pink",                     "rgb": [255, 20, 147]},
  {"name": "Lime Green",                    "rgb": [50, 205, 50]},
  {"name": "Electric Blue",                 "rgb": [0, 191, 255]},
  {"name": "Tangerine",                     "rgb": [255, 140, 0]},
  {"name": "Grape",                         "rgb": [111, 45, 168]}
]